LICENSE.txt
MANIFEST.in
README.md
setup.cfg
setup.py
Pyodbc_Knight.egg-info/PKG-INFO
Pyodbc_Knight.egg-info/SOURCES.txt
Pyodbc_Knight.egg-info/dependency_links.txt
Pyodbc_Knight.egg-info/top_level.txt
mytest/odbc.ini
mytest/odbcinst.ini
mytest/source_env
mytest/test_pyodbc.py
mytest/test_pyodbcc_wsgi.py
src/buffer.cpp
src/buffer.h
src/cnxninfo.cpp
src/cnxninfo.h
src/connection.cpp
src/connection.h
src/cursor.cpp
src/cursor.h
src/dbspecific.h
src/errors.cpp
src/errors.h
src/getdata.cpp
src/getdata.h
src/params.cpp
src/params.h
src/pyodbc.h
src/pyodbc.pyi
src/pyodbccompat.cpp
src/pyodbccompat.h
src/pyodbcdbg.cpp
src/pyodbcmodule.cpp
src/pyodbcmodule.h
src/resource.h
src/row.cpp
src/row.h
src/textenc.cpp
src/textenc.h
src/wrapper.h
tests2/accesstests.py
tests2/dbapi20.py
tests2/dbapitests.py
tests2/empty.accdb
tests2/empty.mdb
tests2/exceltests.py
tests2/informixtests.py
tests2/mysqltests.py
tests2/pgtests.py
tests2/sqldwtests.py
tests2/sqlite.db
tests2/sqlitetests.py
tests2/sqlservertests.py
tests2/test.py
tests2/test.xls
tests2/testbase.py
tests2/testutils.py
tests2/testutils.pyc
tests3/accesstests.py
tests3/dbapi20.py
tests3/dbapitests.py
tests3/empty.accdb
tests3/empty.mdb
tests3/exceltests.py
tests3/informixtests.py
tests3/issue802.py
tests3/mysqltests.py
tests3/pgtests.py
tests3/sparktests.py
tests3/sqldwtests.py
tests3/sqlitetests.py
tests3/sqlservertests.py
tests3/test.py
tests3/testbase.py
tests3/testutils.py